MANIFEST.in
README.rst
setup.py
matchreporter/__init__.py
matchreporter/constants.py
matchreporter/matchreporter_cli.py
matchreporter.egg-info/PKG-INFO
matchreporter.egg-info/SOURCES.txt
matchreporter.egg-info/dependency_links.txt
matchreporter.egg-info/entry_points.txt
matchreporter.egg-info/not-zip-safe
matchreporter.egg-info/requires.txt
matchreporter.egg-info/top_level.txt