Metadata-Version: 1.1
Name: matchreporter
Version: 0.2
Summary: Creates analysis reports for GAA matches
Home-page: https://github.com/moynihanrory/matchreporter
Author: Rory Moynihan
Author-email: ruaraidho@gmail.com
License: MIT
Keywords: matchreporter
Platform: UNKNOWN
Classifier: Development Status :: 3 - Alpha
Classifier: License :: OSI Approved :: MIT License
Classifier: Programming Language :: Python :: 3.5
Classifier: Natural Language :: English
Classifier: Topic :: Text Processing :: Linguistic
